odoo/addons/ssi_task_project_manager/README.rst
odoo/addons/ssi_task_project_manager/__init__.py
odoo/addons/ssi_task_project_manager/__manifest__.py
odoo/addons/ssi_task_project_manager/i18n/ssi_task_project_manager.pot
odoo/addons/ssi_task_project_manager/models/__init__.py
odoo/addons/ssi_task_project_manager/models/project_task.py
odoo/addons/ssi_task_project_manager/static/description/icon.png
odoo/addons/ssi_task_project_manager/views/project_task_views.xml
odoo14_addon_ssi_task_project_manager-14.0.1.2.0.dist-info/METADATA
odoo14_addon_ssi_task_project_manager-14.0.1.2.0.dist-info/WHEEL
odoo14_addon_ssi_task_project_manager-14.0.1.2.0.dist-info/top_level.txt
odoo14_addon_ssi_task_project_manager-14.0.1.2.0.dist-info/RECORD
